twelve_angry_llms/__init__.py
twelve_angry_llms/clients/base.py
twelve_angry_llms/judge.py
twelve_angry_llms/jury.py
twelve_angry_llms/metrics.py
twelve_angry_llms/py.typed
twelve_angry_llms/tasks.py
twelve_angry_llms/types.py
twelve_angry_llms-0.1.0.dist-info/WHEEL
twelve_angry_llms-0.1.0.dist-info/METADATA
twelve_angry_llms-0.1.0.dist-info/RECORD
