Metadata-Version: 2.3
Name: twelve-angry-llms
Version: 0.1.0
Summary: Add your description here
Author: meghdadFar
Author-email: meghdadFar <meghdad.farahmand@gmail.com>
Requires-Dist: openai>=1.0.0
Requires-Dist: pydantic>=2.0.0
Requires-Python: >=3.11
